formatting_library/__init__.py
formatting_library/core.py
formatting_library/_bin/darwin/bef98
formatting_library/_bin/darwin/lci
formatting_library/_bin/linux/bef98
formatting_library/_bin/linux/lci
formatting_library/_bin/windows/lci.exe
formatting_library-1.2.5.1.dist-info/METADATA
formatting_library-1.2.5.1.dist-info/WHEEL
formatting_library-1.2.5.1.dist-info/licenses/LICENSE
formatting_library-1.2.5.1.dist-info/RECORD
