Metadata-Version: 2.4
Name: formatting-library
Version: 1.2.5.1
Summary: A Python library for terminal text formatting, colors, and ASCII art
Project-URL: Homepage, https://github.com/Kundaliel/formatting_library
Project-URL: Repository, https://github.com/Kundaliel/formatting_library
Project-URL: Issues, https://github.com/Kundaliel/formatting_library/issues
Project-URL: PyPI, https://pypi.org/project/formatting-library/
Author-email: Kundaliel <kundaliel.official@gmail.com>
License: MIT License
License-File: LICENSE
Keywords: C,ansi,ascii,colors,formatting,terminal
Classifier: Development Status :: 4 - Beta
Classifier: Intended Audience :: Developers
Classifier: License :: OSI Approved :: MIT License
Classifier: Programming Language :: Python :: 3
Classifier: Programming Language :: Python :: 3.8
Classifier: Programming Language :: Python :: 3.9
Classifier: Programming Language :: Python :: 3.10
Classifier: Programming Language :: Python :: 3.11
Classifier: Programming Language :: Python :: 3.12
Classifier: Topic :: Multimedia :: Graphics
Classifier: Topic :: Terminals
Classifier: Topic :: Text Processing
Requires-Python: >=3.8
Requires-Dist: pillow>=8.0.0
Provides-Extra: dev
Requires-Dist: black; extra == 'dev'
Requires-Dist: flake8; extra == 'dev'
Requires-Dist: isort; extra == 'dev'
Requires-Dist: pytest>=6.0; extra == 'dev'
